phhelper/__init__.py
phhelper/aws_lambda_helper.py
phhelper/aws_lambda_logging.py
phhelper-0.9.7.dist-info/LICENSE
phhelper-0.9.7.dist-info/METADATA
phhelper-0.9.7.dist-info/WHEEL
phhelper-0.9.7.dist-info/top_level.txt
phhelper-0.9.7.dist-info/RECORD
