Metadata-Version: 2.1
Name: phhelper
Version: 0.9.7
Summary: Python Handler Helper for Lambda
Home-page: https://github.com/lhgomes/phhelper
Author: Luiz Henrique Gomes
Author-email: lhgnet@gmail.com
License: MIT
Platform: UNKNOWN
Classifier: Programming Language :: Python :: 3
Classifier: License :: OSI Approved :: MIT License
Classifier: Operating System :: OS Independent
Requires-Python: >=3.6
